{
	"configurations" : 
	[
		{
			"directories" : 
			[
				{
					"build" : ".",
					"jsonFile" : "directory-.-Debug-f5ebdc15457944623624.json",
					"minimumCMakeVersion" : 
					{
						"string" : "3.21"
					},
					"projectIndex" : 0,
					"source" : ".",
					"targetIndexes" : 
					[
						0
					]
				}
			],
			"name" : "Debug",
			"projects" : 
			[
				{
					"directoryIndexes" : 
					[
						0
					],
					"name" : "no_75",
					"targetIndexes" : 
					[
						0
					]
				}
			],
			"targets" : 
			[
				{
					"directoryIndex" : 0,
					"id" : "no_75::@6890427a1f51a3e7e1df",
					"jsonFile" : "target-no_75-Debug-23ab5f9456c4888f6074.json",
					"name" : "no_75",
					"projectIndex" : 0
				}
			]
		}
	],
	"kind" : "codemodel",
	"paths" : 
	{
		"build" : "/Users/xupeng/Documents/C_advance/reexamination_training/no_75/cmake-build-debug",
		"source" : "/Users/xupeng/Documents/C_advance/reexamination_training/no_75"
	},
	"version" : 
	{
		"major" : 2,
		"minor" : 3
	}
}
